collective.dms.scanbehavior-1.3.2-py3.12-nspkg.pth
collective/dms/scanbehavior/__init__.py
collective/dms/scanbehavior/configure.zcml
collective/dms/scanbehavior/interfaces.py
collective/dms/scanbehavior/setuphandlers.py
collective/dms/scanbehavior/testing.py
collective/dms/scanbehavior/testing.zcml
collective/dms/scanbehavior/upgrades.py
collective/dms/scanbehavior/behaviors/__init__.py
collective/dms/scanbehavior/behaviors/behaviors.py
collective/dms/scanbehavior/behaviors/configure.zcml
collective/dms/scanbehavior/browser/__init__.py
collective/dms/scanbehavior/browser/configure.zcml
collective/dms/scanbehavior/browser/static/.gitkeep
collective/dms/scanbehavior/locales/collective.dms.scanbehavior.pot
collective/dms/scanbehavior/locales/update.sh
collective/dms/scanbehavior/locales/fr/LC_MESSAGES/collective.dms.scanbehavior.po
collective/dms/scanbehavior/profiles/default/browserlayer.xml
collective/dms/scanbehavior/profiles/default/catalog.xml
collective/dms/scanbehavior/profiles/default/collectivedmsscanbehavior_marker.txt
collective/dms/scanbehavior/profiles/default/metadata.xml
collective/dms/scanbehavior/profiles/testing/metadata.xml
collective/dms/scanbehavior/tests/__init__.py
collective/dms/scanbehavior/tests/test_robot.py
collective/dms/scanbehavior/tests/test_setup.py
collective/dms/scanbehavior/tests/robot/.gitkeep
collective/dms/scanbehavior/tests/robot/test_scanbehavior.robot
collective_dms_scanbehavior-1.3.2.dist-info/METADATA
collective_dms_scanbehavior-1.3.2.dist-info/WHEEL
collective_dms_scanbehavior-1.3.2.dist-info/entry_points.txt
collective_dms_scanbehavior-1.3.2.dist-info/namespace_packages.txt
collective_dms_scanbehavior-1.3.2.dist-info/top_level.txt
collective_dms_scanbehavior-1.3.2.dist-info/RECORD
