Metadata-Version: 2.4
Name: collective.dms.scanbehavior
Version: 1.3.2
Summary: Behavior adding scan metadata
Home-page: http://pypi.python.org/pypi/collective.dms.scanbehavior
Author: Franck NGAHA, Stephan Geulette
Author-email: franck.o.ngaha@gmail.com, sgeulette@imio.be
License: GPL
Keywords: Python Zope Plone
Classifier: Environment :: Web Environment
Classifier: Framework :: Plone
Classifier: Framework :: Plone :: 4.3
Classifier: Programming Language :: Python
Classifier: Programming Language :: Python :: 2.7
Requires-Dist: plone.api
Requires-Dist: setuptools
Requires-Dist: plone.app.dexterity
Requires-Dist: plone.behavior
Requires-Dist: plone.directives.form
Requires-Dist: zope.schema
Requires-Dist: zope.interface
Requires-Dist: zope.component
Requires-Dist: rwproperty
Provides-Extra: test
Requires-Dist: plone.app.testing; extra == "test"
Requires-Dist: plone.app.robotframework[debug]; extra == "test"
Dynamic: author
Dynamic: author-email
Dynamic: classifier
Dynamic: description
Dynamic: home-page
Dynamic: keywords
Dynamic: license
Dynamic: provides-extra
Dynamic: requires-dist
Dynamic: summary
